jiso_droid/__init__.py
jiso_droid/jiso.py
jiso_droid/lib/__init__.py
jiso_droid/lib/config.py
jiso_droid/lib/keystore.py
jiso_droid/lib/models.py
jiso_droid/lib/signer.py
jiso_droid-1.1.0.dev9.dist-info/METADATA
jiso_droid-1.1.0.dev9.dist-info/WHEEL
jiso_droid-1.1.0.dev9.dist-info/entry_points.txt
jiso_droid-1.1.0.dev9.dist-info/top_level.txt
jiso_droid-1.1.0.dev9.dist-info/RECORD
