Metadata-Version: 2.4
Name: jiso-droid
Version: 1.1.0.dev9
Summary: JISO-DROID - Keystore Generator & APK Signing Tool
Author: Jhosua
Author-email: echobytehax@gmail.com
Classifier: Programming Language :: Python :: 3
Classifier: License :: OSI Approved :: MIT License
Classifier: Operating System :: OS Independent
Requires-Python: >=3.9
Dynamic: author
Dynamic: author-email
Dynamic: classifier
Dynamic: description
Dynamic: description-content-type
Dynamic: requires-python
Dynamic: summary
